django_keyrock-0.0.2.dist-info/DESCRIPTION.rst
django_keyrock-0.0.2.dist-info/METADATA
django_keyrock-0.0.2.dist-info/RECORD
django_keyrock-0.0.2.dist-info/WHEEL
django_keyrock-0.0.2.dist-info/metadata.json
django_keyrock-0.0.2.dist-info/top_level.txt
keyrock/__init__.py
keyrock/context_processors.py
keyrock/urls.py
keyrock/views.py
