Metadata-Version: 2.0
Name: django-keyrock
Version: 0.0.2
Summary: KeyRock Identity Manager client for Django
Home-page: https://github.com/Glamping-Hub/django-keyrock
Author: Glamping Hub
Author-email: it@glampinghub.com
License: BSD
Keywords: keyrock idm identity django
Platform: UNKNOWN
Classifier: Development Status :: 4 - Beta
Classifier: Environment :: Web Environment
Classifier: Framework :: Django
Classifier: Intended Audience :: Developers
Classifier: License :: OSI Approved :: BSD License
Classifier: Operating System :: OS Independent
Classifier: Programming Language :: Python :: 2 :: Only
Classifier: Topic :: Software Development :: Libraries :: Python Modules
Classifier: Topic :: Internet
Requires: Django (>=1.5.0)
Requires: requests (>=2.0.0)
Requires: requests_oauthlib (>=0.6.0)
